mindsync/__init__.py
mindsync/__main__.py
mindsync/api.py
mindsync/api_test.py
mindsync/cli.py
mindsync/cli_handler.py
mindsync/cli_handler_test.py
mindsync/cli_test.py
mindsync/exc.py
mindsync-0.1.27.dist-info/LICENSE
mindsync-0.1.27.dist-info/METADATA
mindsync-0.1.27.dist-info/WHEEL
mindsync-0.1.27.dist-info/entry_points.txt
mindsync-0.1.27.dist-info/top_level.txt
mindsync-0.1.27.dist-info/RECORD
