Metadata-Version: 2.1
Name: mindsync
Version: 0.1.27
Summary: Mindsync API
Home-page: https://github.com/mindsync-ai/mindsync-api-python
Author: Mindsync
Author-email: support@mindsync.ai
License: Apache 2.0
Project-URL: Bug Tracker, https://github.com/mindsync-ai/mindsync-api-python/issues
Keywords: Mindsync,API
Platform: UNKNOWN
Classifier: Programming Language :: Python :: 3
Classifier: Operating System :: OS Independent
Requires-Python: >=3.6
License-File: LICENSE
Requires-Dist: aiohttp (==3.7.4.post0)
